kuws/__init__.py
kuws/command_line_utility.py
kuws/utilities/__init__.py
kuws/utilities/domains.py
kuws/utilities/redirects.py
kuws/utilities/ssl_utilities.py
kuws/utilities/youtube.py
kuws-0.0.7.dist-info/LICENSE
kuws-0.0.7.dist-info/METADATA
kuws-0.0.7.dist-info/WHEEL
kuws-0.0.7.dist-info/entry_points.txt
kuws-0.0.7.dist-info/top_level.txt
kuws-0.0.7.dist-info/RECORD
