Metadata-Version: 2.1
Name: kuws
Version: 0.0.7
Summary: A set of python scripts for common web tasks
Home-page: https://github.com/Descent098/kuws
Author: Kieran Wood
Author-email: kieran@canadiancoding.ca
License: UNKNOWN
Platform: UNKNOWN
Classifier: Programming Language :: Python :: 3
Classifier: License :: OSI Approved :: MIT License
Classifier: Operating System :: OS Independent
Classifier: Development Status :: 7 - Inactive
Requires-Dist: requests
Requires-Dist: pytube3
Requires-Dist: docopt
Provides-Extra: dev
Requires-Dist: nox ; extra == 'dev'
Requires-Dist: pytest ; extra == 'dev'
Requires-Dist: mkdocs ; extra == 'dev'
